LatticePy/__init__.py
LatticePy/all_lattices.py
LatticePy/objects.py
latticepy-0.3.2.dist-info/METADATA
latticepy-0.3.2.dist-info/WHEEL
latticepy-0.3.2.dist-info/licenses/LICENSE.md
latticepy-0.3.2.dist-info/RECORD
