Metadata-Version: 2.3
Name: LatticePy
Version: 0.3.2
Summary: A package for simulating biomolecules on a lattice.
Project-URL: Source, https://github.com/sohitmiglani/LatticePy
Project-URL: Issues, https://github.com/sohitmiglani/LatticePy/issues
Author-email: Sohit Miglani <sohitmiglani@gmail.com>
License: MIT License
License-File: LICENSE.md
Classifier: Intended Audience :: Science/Research
Classifier: License :: OSI Approved :: MIT License
Classifier: Operating System :: OS Independent
Classifier: Programming Language :: Python :: 3.8
Classifier: Programming Language :: Python :: 3.9
Classifier: Programming Language :: Python :: 3.10
Classifier: Programming Language :: Python :: 3.11
Classifier: Programming Language :: Python :: 3.12
Requires-Python: >=3.8
Requires-Dist: matplotlib<=3.9.2
Requires-Dist: networkx<=3.3
Requires-Dist: numpy<=2.1.0
Requires-Dist: pandas<=2.2.2
Requires-Dist: plotly<=5.23.0
Requires-Dist: seaborn<=0.13.2
